OuterPoly/OuterPoly.py
OuterPoly/__init__.py
OuterPoly-1.0.3.dist-info/LICENSE
OuterPoly-1.0.3.dist-info/METADATA
OuterPoly-1.0.3.dist-info/WHEEL
OuterPoly-1.0.3.dist-info/top_level.txt
OuterPoly-1.0.3.dist-info/RECORD
