Metadata-Version: 2.1
Name: OuterPoly
Version: 1.0.3
Summary: A Python package to find outer polygons equi-distant from the inner polygon
Home-page: https://github.com/AnoopANair/OuterPoly
Author: Anoop A Nair
Author-email: mailtoanoop71@gmail.com
License: MIT
Platform: UNKNOWN
Classifier: License :: OSI Approved :: MIT License
Classifier: Programming Language :: Python :: 3
Classifier: Programming Language :: Python :: 3.7
Requires-Python: >=3.6
